odoo/addons/hotel/README.rst
odoo/addons/hotel/__init__.py
odoo/addons/hotel/__manifest__.py
odoo/addons/hotel/LICENSE/LICENSE
odoo/addons/hotel/data/hotel-color.png
odoo/addons/hotel/data/hotel-grey.png
odoo/addons/hotel/data/hotel_data.xml
odoo/addons/hotel/data/hotel_sequence.xml
odoo/addons/hotel/data/paperformat.xml
odoo/addons/hotel/i18n/bg.po
odoo/addons/hotel/i18n/da.po
odoo/addons/hotel/i18n/es.po
odoo/addons/hotel/i18n/fr.po
odoo/addons/hotel/i18n/fr_BE.po
odoo/addons/hotel/i18n/hotel.pot
odoo/addons/hotel/i18n/hr.po
odoo/addons/hotel/i18n/pt_BR.po
odoo/addons/hotel/i18n/sv.po
odoo/addons/hotel/models/__init__.py
odoo/addons/hotel/models/account_invoice.py
odoo/addons/hotel/models/hotel_folio.py
odoo/addons/hotel/models/hotel_folio_line.py
odoo/addons/hotel/models/hotel_room.py
odoo/addons/hotel/models/hotel_room_amenities.py
odoo/addons/hotel/models/hotel_room_type.py
odoo/addons/hotel/models/hotel_service_line.py
odoo/addons/hotel/models/hotel_service_type.py
odoo/addons/hotel/models/hotel_services.py
odoo/addons/hotel/models/product_product.py
odoo/addons/hotel/models/res_company.py
odoo/addons/hotel/readme/CONTRIBUTORS.rst
odoo/addons/hotel/readme/DESCRIPTION.rst
odoo/addons/hotel/report/__init__.py
odoo/addons/hotel/report/hotel_report.py
odoo/addons/hotel/report/hotel_report.xml
odoo/addons/hotel/report/report_hotel_management.xml
odoo/addons/hotel/security/hotel_security.xml
odoo/addons/hotel/security/ir.model.access.csv
odoo/addons/hotel/static/description/Hotel.png
odoo/addons/hotel/static/description/bed.png
odoo/addons/hotel/static/description/book.png
odoo/addons/hotel/static/description/booking.png
odoo/addons/hotel/static/description/car.png
odoo/addons/hotel/static/description/checkin.png
odoo/addons/hotel/static/description/currency.png
odoo/addons/hotel/static/description/fast-food-icons.png
odoo/addons/hotel/static/description/gym.png
odoo/addons/hotel/static/description/head.png
odoo/addons/hotel/static/description/hotel1.png
odoo11_addon_hotel-11.0.1.0.0.99.dev57.dist-info/METADATA
odoo11_addon_hotel-11.0.1.0.0.99.dev57.dist-info/WHEEL
odoo11_addon_hotel-11.0.1.0.0.99.dev57.dist-info/top_level.txt
odoo11_addon_hotel-11.0.1.0.0.99.dev57.dist-info/RECORD
